tnkeeh/__init__.py
tnkeeh/tests.py
tnkeeh/tnkeeh.py
tnkeeh/dictionaries/norm_dict.pl
tnkeeh-0.0.9.dist-info/LICENSE
tnkeeh-0.0.9.dist-info/METADATA
tnkeeh-0.0.9.dist-info/WHEEL
tnkeeh-0.0.9.dist-info/top_level.txt
tnkeeh-0.0.9.dist-info/RECORD
