Metadata-Version: 2.1
Name: tnkeeh
Version: 0.0.9
Summary: UNKNOWN
Home-page: UNKNOWN
Author: Zaid Alyafeai, Maged Saeed
Author-email: arabicmachinelearning@gmail.com
License: MIT
Platform: UNKNOWN
Requires-Python: >=3.6
Requires-Dist: farasapy
Requires-Dist: datasets
